argparse_shell/__init__.py
argparse_shell/argparse_shell.py
argparse_shell/builder.py
argparse_shell/command.py
argparse_shell/constants.py
argparse_shell/decorators.py
argparse_shell/interactive.py
argparse_shell/namespace.py
argparse_shell/utils.py
argparse_shell/wrappers.py
argparse_shell-0.2.0.dist-info/METADATA
argparse_shell-0.2.0.dist-info/WHEEL
argparse_shell-0.2.0.dist-info/licenses/LICENSE
argparse_shell-0.2.0.dist-info/RECORD
