Metadata-Version: 2.4
Name: argparse-shell
Version: 0.2.0
Summary: Create interactive shell programs from arbitrary objects using the argparse and cmd modules
Author-email: Jonas Ehrlich <jonas.ehrlich@umsemi.com>
License-Expression: MIT
License-File: LICENSE
Classifier: Development Status :: 4 - Beta
Classifier: Environment :: Console
Classifier: License :: OSI Approved :: MIT License
Classifier: Natural Language :: English
Classifier: Operating System :: MacOS :: MacOS X
Classifier: Operating System :: POSIX :: Linux
Requires-Python: >=3.11
Requires-Dist: docstring-parser>=0.16
